{"remainingRequest":"C:\\Users\\lgp\\Desktop\\Finance\\node_modules\\vue-loader\\lib\\index.js??vue-loader-options!C:\\Users\\lgp\\Desktop\\Finance\\app\\js\\money\\finance.vue?vue&type=style&index=0&lang=scss&module=true&","dependencies":[{"path":"C:\\Users\\lgp\\Desktop\\Finance\\app\\js\\money\\finance.vue","mtime":1552065845759},{"path":"C:\\Users\\lgp\\Desktop\\Finance\\node_modules\\css-loader\\index.js","mtime":499162500000},{"path":"C:\\Users\\lgp\\Desktop\\Finance\\node_modules\\vue-loader\\lib\\loaders\\stylePostLoader.js","mtime":499162500000},{"path":"C:\\Users\\lgp\\Desktop\\Finance\\node_modules\\px2rem-loader\\index.js","mtime":1522552575000},{"path":"C:\\Users\\lgp\\Desktop\\Finance\\node_modules\\sass-loader\\lib\\loader.js","mtime":499162500000},{"path":"C:\\Users\\lgp\\Desktop\\Finance\\node_modules\\cache-loader\\dist\\cjs.js","mtime":1551889686839},{"path":"C:\\Users\\lgp\\Desktop\\Finance\\node_modules\\vue-loader\\lib\\index.js","mtime":499162500000}],"contextDependencies":[],"result":["\n\n\n\n\n\n\n\n\n\n\n\n\n\n\n\n\n\n\n\n\n\n\n\n\n\n\n\n\n\n\n\n\n\n\n\n\n\n\n\n\n\n@import '../../css/element.scss';\n.panel{\n    @include panel;\n    >h4{\n        border-bottom: 1px solid #ddd;\n    }\n    .content{\n        @include flex;\n        .item{\n            @include flex(row);\n            align-content: center;\n            height: 140px;\n            &::after{\n                content: '';\n                box-sizing: border-box;\n                height: 0;\n                width: 100%;\n                border-bottom: 1px solid #ddd;\n                margin-left: 150px;\n                margin-top: 10px;\n            }\n            &:last-child::after{\n                border-color: #fff;\n            }\n            >img{\n                width: 88px;\n                height: 88px;\n                display: inline-block;\n                margin: 0 32px;\n            }\n            >div{\n                font-size: 32px;\n                color: #333;\n                line-height: 1.8;\n                width: 344px;\n                p{\n                    color: #ff3232;\n                    font-size: 24px;\n                    line-height: 1.1;\n                    white-space: nowrap;\n                    text-overflow: ellipsis;\n                    overflow: hidden;\n                }\n            }\n            >em{\n                color: #ff801a;\n                font-size: 28px;\n            }\n        }\n    }\n}\n",null]}